vbf_parser/__init__.py
vbf_parser/header_extractor.py
vbf_parser/vbf_jsonifier.py
vbf_parser/vbf_parser.py
vbf_parser-1.4.0.dist-info/LICENSE
vbf_parser-1.4.0.dist-info/WHEEL
vbf_parser-1.4.0.dist-info/METADATA
vbf_parser-1.4.0.dist-info/RECORD
