Metadata-Version: 2.1
Name: vbf-parser
Version: 1.4.0
Summary: Simple vbf parser
Home-page: UNKNOWN
License: UNKNOWN
Author: Rafal Slaby
Author-email: rafal.slaby222@gmail.com
Requires-Python: >=3.6
Classifier: License :: OSI Approved :: MIT License
Classifier: Programming Language :: Python :: 3
Classifier: Programming Language :: Python :: 3.7
Classifier: Programming Language :: Python :: 3.8
